godto/__init__.py
godto/api/__init__.py
godto/api/model.py
godto/data/openapi/README.md
godto/data/openapi/v2.0/README.md
godto/data/openapi/v2.0/schema.json
godto/data/openapi/v3.0/README.md
godto/data/openapi/v3.0/schema.json
godto/data/openapi/v3.0/schema.yaml
godto/openapi/README.md
godto/openapi/v3.py
godto-0.0.5.dist-info/LICENSE
godto-0.0.5.dist-info/METADATA
godto-0.0.5.dist-info/WHEEL
godto-0.0.5.dist-info/top_level.txt
godto-0.0.5.dist-info/RECORD
