Metadata-Version: 2.1
Name: godto
Version: 0.0.5
Summary: Data Transfer Object (DTO) codegen from OpenAPI JSON schemas
Home-page: https://github.com/lmmx/godto
Author: Louis Maddox
Author-email: louismmx@gmail.com
Maintainer: Louis Maddox
Maintainer-email: louismmx@gmail.com
License: MIT
Project-URL: Bug Tracker, https://github.com/lmmx/godto/issues
Project-URL: Source Code, https://github.com/lmmx/godto
Classifier: Development Status :: 4 - Beta
Classifier: Intended Audience :: Developers
Classifier: Natural Language :: English
Classifier: License :: OSI Approved :: MIT License
Classifier: Operating System :: OS Independent
Classifier: Programming Language :: Python
Classifier: Programming Language :: Python :: Implementation :: CPython
Classifier: Programming Language :: Python :: 3
Classifier: Programming Language :: Python :: 3.9
Classifier: Programming Language :: Python :: 3.10
Classifier: Topic :: Internet :: WWW/HTTP
Requires-Python: >=3.9
License-File: LICENSE
Requires-Dist: defopt
Requires-Dist: jsonschema
Requires-Dist: pydantic[email]
Requires-Dist: ujson
Provides-Extra: dev
Requires-Dist: coverage[toml] (>=5.5) ; extra == 'dev'
Requires-Dist: pytest ; extra == 'dev'
Requires-Dist: pre-commit ; extra == 'dev'
Provides-Extra: docs
Provides-Extra: tests
Requires-Dist: coverage[toml] (>=5.5) ; extra == 'tests'
Requires-Dist: pytest ; extra == 'tests'
